lisette/__init__.py
lisette/_modidx.py
lisette/core.py
lisette/usage.py
lisette-0.0.34.dist-info/licenses/LICENSE
lisette-0.0.34.dist-info/METADATA
lisette-0.0.34.dist-info/WHEEL
lisette-0.0.34.dist-info/entry_points.txt
lisette-0.0.34.dist-info/top_level.txt
lisette-0.0.34.dist-info/RECORD
