Metadata-Version: 2.4
Name: lisette
Version: 0.0.34
Summary: litellm helper
Author-email: AnswerDotAI <support@answer.ai>
License: Apache-2.0
Project-URL: Repository, https://github.com/AnswerDotAI/lisette
Project-URL: Documentation, https://lisette.answer.ai/
Keywords: nbdev,jupyter,notebook,python
Classifier: Natural Language :: English
Classifier: Intended Audience :: Developers
Classifier: Development Status :: 3 - Alpha
Classifier: Programming Language :: Python :: 3
Classifier: Programming Language :: Python :: 3 :: Only
Requires-Python: >=3.9
License-File: LICENSE
Requires-Dist: litellm==1.80.11
Requires-Dist: numpydoc
Requires-Dist: toolslm
Requires-Dist: fastcore>=1.9.2
Provides-Extra: dev
Requires-Dist: ipython; extra == "dev"
Requires-Dist: pycachy>=0.0.6; extra == "dev"
Requires-Dist: fastlite; extra == "dev"
Requires-Dist: nbdev; extra == "dev"
Requires-Dist: pillow; extra == "dev"
Dynamic: license-file
